pycount_xilinx/__init__.py
pycount_xilinx/plotting.py
pycount_xilinx/pycounts.py
pycount_xilinx-0.1.0.dist-info/LICENSE
pycount_xilinx-0.1.0.dist-info/WHEEL
pycount_xilinx-0.1.0.dist-info/METADATA
pycount_xilinx-0.1.0.dist-info/RECORD
