Metadata-Version: 2.1
Name: pycount-xilinx
Version: 0.1.0
Summary: Count words in a text file.
License: MIT
Author: Xilinx
Requires-Python: >=3.9,<4.0
Classifier: License :: OSI Approved :: MIT License
Classifier: Programming Language :: Python :: 3
Classifier: Programming Language :: Python :: 3.10
Classifier: Programming Language :: Python :: 3.9
Requires-Dist: matplotlib (>=3.5.2,<4.0.0)
